ijp/__init__.py
ijp/incremental_json.py
ijp-1.0.0.dist-info/METADATA
ijp-1.0.0.dist-info/WHEEL
ijp-1.0.0.dist-info/top_level.txt
ijp-1.0.0.dist-info/RECORD
