Metadata-Version: 2.1
Name: ijp
Version: 1.0.0
Summary: An incremental JSON parser for handling JSON data generated by LLMs.
Author: JSH
Author-email: JSH <jsh6789@gmail.com>
License: License :: OSI Approved :: The Unlicense (Unlicense)
Project-URL: Repository, https://github.com/jsh6789/ijp
Requires-Python: >=3.9
